libfile/__init__.py
rlane_libfile-1.0.2.dist-info/METADATA
rlane_libfile-1.0.2.dist-info/WHEEL
rlane_libfile-1.0.2.dist-info/entry_points.txt
rlane_libfile-1.0.2.dist-info/licenses/LICENSE
rlane_libfile-1.0.2.dist-info/RECORD
