Metadata-Version: 2.1
Name: rlane-libfile
Version: 1.0.2
Summary: Represent a filesystem item such as a file or folder
Keywords: libfile
Author-Email: Russel Lane <russel@rlane.com>
License: MIT
Classifier: Development Status :: 4 - Beta
Classifier: Intended Audience :: Developers
Classifier: License :: OSI Approved :: MIT License
Classifier: Programming Language :: Python :: 3
Classifier: Topic :: Software Development :: Libraries :: Python Modules
Project-URL: Homepage, https://github.com/russellane/libfile
Requires-Python: >=3.10
Requires-Dist: loguru>=0.7.2
